README.rst
setup.py
bloomfilter/__init__.py
bloomfilter/bloomfilter.py
bloomfilter4py3.egg-info/PKG-INFO
bloomfilter4py3.egg-info/SOURCES.txt
bloomfilter4py3.egg-info/dependency_links.txt
bloomfilter4py3.egg-info/requires.txt
bloomfilter4py3.egg-info/top_level.txt