Metadata-Version: 1.1
Name: bloomfilter4py3
Version: 1.1.1
Summary: A Bloomfilter implement in pure python for python3.
Home-page: https://github.com/coneco/Bloomfilter4py3
Author: coNEco
Author-email: coneco@outlook.com
License: MIT
Keywords: bloomfilter
Platform: UNKNOWN
Classifier: Development Status :: 5 - Production/Stable
Classifier: Intended Audience :: Developers
Classifier: Topic :: Software Development :: Libraries :: Python ModulesLicense :: OSI Approved :: MIT License
Classifier: Programming Language :: Python :: 3
Classifier: Programming Language :: Python :: 3.3
Classifier: Programming Language :: Python :: 3.4
Classifier: Programming Language :: Python :: 3.5
Classifier: Programming Language :: Python :: 3.6
Classifier: Programming Language :: Python :: 3 :: Only
